README.txt
setup.py
aiowebsocketclient/__init__.py
aiowebsocketclient/connector.py
aiowebsocketclient/log.py
aiowebsocketclient.egg-info/PKG-INFO
aiowebsocketclient.egg-info/SOURCES.txt
aiowebsocketclient.egg-info/dependency_links.txt
aiowebsocketclient.egg-info/requires.txt
aiowebsocketclient.egg-info/top_level.txt
tests/__init__.py
tests/tests.py